mosaik_components/pandapower/__init__.py
mosaik_components/pandapower/simulator.py
mosaik_pandapower_2-0.3.6.dist-info/METADATA
mosaik_pandapower_2-0.3.6.dist-info/WHEEL
mosaik_pandapower_2-0.3.6.dist-info/licenses/LICENSE
mosaik_pandapower_2-0.3.6.dist-info/RECORD
