Metadata-Version: 2.3
Name: mosaik-pandapower-2
Version: 0.3.6
Summary: An adapter to connect mosaik to pandapower
Author-email: Eike Schulte <eike.schulte@offis.de>
License-Expression: MIT
License-File: LICENSE
Requires-Python: >=3.9
Requires-Dist: loguru~=0.7.2
Requires-Dist: mosaik-api-v3~=3.0.4
Requires-Dist: pandapower~=2.14
Provides-Extra: numba
Requires-Dist: numba~=0.58.1; extra == 'numba'
Provides-Extra: simbench
Requires-Dist: simbench~=1.4.0; extra == 'simbench'
